{
  "github": {
    "branch": "gh-pages",
    "automaticallyMergePR": false,
    "api": {
      "tiersForApi": "Github Free/Pro/Team (default)",
      "hostname": ""
    },
    "otherRepo": [],
    "workflow": {
      "name": "",
      "commitMessage": "Publish"
    },
    "tokenPath": ".obsidian/plugins/obsidian-mkdocs-publisher/env",
    "repo": "Study-Notes",
    "user": "Make-UpWorkClub",
    "rateLimit": 4924,
    "verifiedRepo": true
  },
  "upload": {
    "behavior": "obsidian",
    "subFolder": "",
    "defaultName": "docs/hidden",
    "rootFolder": "docs",
    "yamlFolderKey": "category",
    "frontmatterTitle": {
      "enable": true,
      "key": "name"
    },
    "replaceTitle": [],
    "autoclean": {
      "enable": true,
      "excluded": [
        "docs/assets/js",
        "docs/assets/meta",
        "docs/assets/css",
        "tags.md",
        "graph.md"
      ]
    },
    "folderNote": {
      "enable": true,
      "rename": "index.md"
    },
    "metadataExtractorPath": "",
    "replacePath": []
  },
  "conversion": {
    "hardbreak": false,
    "dataview": false,
    "censorText": [],
    "tags": {
      "inline": true,
      "exclude": [],
      "fields": []
    },
    "links": {
      "internal": true,
      "unshared": false,
      "wiki": false
    }
  },
  "embed": {
    "attachments": true,
    "keySendFile": [
      "image"
    ],
    "notes": true,
    "folder": "docs/assets/img"
  },
  "plugin": {
    "shareKey": "share",
    "fileMenu": false,
    "editorMenu": false,
    "excludedFolder": [],
    "copyLink": {
      "enable": false,
      "links": "",
      "removePart": [],
      "addCmd": false
    },
    "noticeError": true,
    "displayModalRepoEditing": false,
    "migrated": true,
    "shareAll": {
      "enable": true,
      "excludedFileName": "DRAFT"
    }
  },
  "tabsID": "github-configuration"
}